Metadata-Version: 2.4
Name: brainglobe-segmentation
Version: 1.3.3
Summary: Segmentation of anatomical structures in a common coordinate space
Author-email: "Adam Tyson, Horst Obenhaus" <code@adamltyson.com>
License: BSD-3-Clause
Project-URL: Homepage, https://brainglobe.info/
Project-URL: Source Code, https://github.com/brainglobe/brainglobe-segmentation
Project-URL: Bug Tracker, https://github.com/brainglobe/brainglobe-segmentation/issues
Project-URL: Documentation, https://brainglobe.info/documentation/brainglobe-segmentation/index.html
Project-URL: User Support, https://forum.image.sc/tag/brainglobe
Classifier: Development Status :: 4 - Beta
Classifier: Framework :: napari
Classifier: Intended Audience :: Developers
Classifier: Intended Audience :: Science/Research
Classifier: Operating System :: OS Independent
Classifier: Programming Language :: Python
Classifier: Programming Language :: Python :: 3
Classifier: Programming Language :: Python :: 3.11
Classifier: Programming Language :: Python :: 3.12
Classifier: Programming Language :: Python :: 3.13
Requires-Python: >=3.11
License-File: LICENSE
Requires-Dist: brainglobe-atlasapi>=2.0.1
Requires-Dist: brainglobe-napari-io>=0.3.0
Requires-Dist: brainglobe-utils>=0.5.0
Requires-Dist: napari!=0.6.0,>=0.5
Requires-Dist: numpy
Requires-Dist: pandas[hdf5]
Requires-Dist: qtpy
Requires-Dist: scikit-image
Requires-Dist: scipy
Requires-Dist: tifffile
Requires-Dist: qt-niu
Provides-Extra: dev
Requires-Dist: black; extra == "dev"
Requires-Dist: gitpython; extra == "dev"
Requires-Dist: pre-commit; extra == "dev"
Requires-Dist: pytest; extra == "dev"
Requires-Dist: coverage; extra == "dev"
Requires-Dist: pytest-cov; extra == "dev"
Requires-Dist: pytest-qt; extra == "dev"
Requires-Dist: napari-time-slicer; extra == "dev"
Dynamic: license-file
